Metadata-Version: 1.0
Name: vsearch-evgeny-1957
Version: 1.0
Summary: The Head First Python Search Tools
Home-page: UNKNOWN
Author: HF Python 2e
Author-email: evyakush@gmail.com
License: UNKNOWN
Platform: UNKNOWN
